[{"kind": "youtube#commentThread", "etag": "\"p4VTdlkQv3HQeTEaXgvLePAydmU/6YpSRPqeuZ47wv7ymc8Ey77bkzY\"", "id": "UgwjmgEL8uYJdwiO1ll4AaABAg", "snippet": {"videoId": "b-TCwqlx2fg", "topLevelComment": {"kind": "youtube#comment", "etag": "\"p4VTdlkQv3HQeTEaXgvLePAydmU/qmaDA0m61xLfdZzRcAH10jsdY-8\"", "id": "UgwjmgEL8uYJdwiO1ll4AaABAg", "snippet": {"authorDisplayName": "Keesch 5", "authorProfileImageUrl": "https://yt3.ggpht.com/a/AGF-l7_HKiud8NBrwyOXYFqZjIJFynCsgJSf7JTt0Q=s48-c-k-c0xffffffff-no-rj-mo", "authorChannelUrl": "http://www.youtube.com/channel/UCl3Jkg3mFfoCSQM6b2mmO0g", "authorChannelId": {"value": "UCl3Jkg3mFfoCSQM6b2mmO0g"}, "videoId": "b-TCwqlx2fg", "textDisplay": "interlacing in 2019?", "textOriginal": "interlacing in 2019?", "canRate": true, "viewerRating": "none", "likeCount": 0, "publishedAt": "2019-12-26T22:30:19.000Z", "updatedAt": "2019-12-26T22:30:19.000Z"}}, "canReply": true, "totalReplyCount": 0, "isPublic": true}}, {"kind": "youtube#commentThread", "etag": "\"p4VTdlkQv3HQeTEaXgvLePAydmU/JK1Ck7nFsHQ9hgYVwTBe1X8xTeI\"", "id": "Ugymq27rfvdP9CcNvT14AaABAg", "snippet": {"videoId": "b-TCwqlx2fg", "topLevelComment": {"kind": "youtube#comment", "etag": "\"p4VTdlkQv3HQeTEaXgvLePAydmU/mD568F-R8gHlQw5yOgLabRiqHV4\"", "id": "Ugymq27rfvdP9CcNvT14AaABAg", "snippet": {"authorDisplayName": "Graeme Evans", "authorProfileImageUrl": "https://yt3.ggpht.com/a/AGF-l78XnMtqBVo6G11Nn0P5ytazqt_Q9iUaTbObfg=s48-c-k-c0xffffffff-no-rj-mo", "authorChannelUrl": "http://www.youtube.com/channel/UCAtarhpqAD9xC3BrAlp9yCw", "authorChannelId": {"value": "UCAtarhpqAD9xC3BrAlp9yCw"}, "videoId": "b-TCwqlx2fg", "textDisplay": "so daisy is in the thumbnail just to get clikcs then. because all she does is sit there and make doing nothing look good.", "textOriginal": "so daisy is in the thumbnail just to get clikcs then. because all she does is sit there and make doing nothing look good.", "canRate": true, "viewerRating": "none", "likeCount": 0, "publishedAt": "2019-12-26T21:31:42.000Z", "updatedAt": "2019-12-26T21:31:42.000Z"}}, "canReply": true, "totalReplyCount": 0, "isPublic": true}}, {"kind": "youtube#commentThread", "etag": "\"p4VTdlkQv3HQeTEaXgvLePAydmU/Zymlf0fUR_pa8p0GAhb_riN85D8\"", "id": "Ugy2YbSWOM9-PGptWrJ4AaABAg", "snippet": {"videoId": "b-TCwqlx2fg", "topLevelComment": {"kind": "youtube#comment", "etag": "\"p4VTdlkQv3HQeTEaXgvLePAydmU/6wUjim4GpbKd7K0RMdHNXN-Z7K0\"", "id": "Ugy2YbSWOM9-PGptWrJ4AaABAg", "snippet": {"authorDisplayName": "DemonAssassinEB", "authorProfileImageUrl": "https://yt3.ggpht.com/a/AGF-l79h7F4VBUPLzPgVF3cmPigHsydoOd4VcfQIWQ=s48-c-k-c0xffffffff-no-rj-mo", "authorChannelUrl": "http://www.youtube.com/channel/UCz9lthrFmANtsLFRauDfbQA", "authorChannelId": {"value": "UCz9lthrFmANtsLFRauDfbQA"}, "videoId": "b-TCwqlx2fg", "textDisplay": "We can call is Welsh Wars", "textOriginal": "We can call is Welsh Wars", "canRate": true, "viewerRating": "none", "likeCount": 1, "publishedAt": "2019-12-26T16:12:04.000Z", "updatedAt": "2019-12-26T16:12:04.000Z"}}, "canReply": true, "totalReplyCount": 0, "isPublic": true}}, {"kind": "youtube#commentThread", "etag": "\"p4VTdlkQv3HQeTEaXgvLePAydmU/uGDu5G_wM2hWlNv21_T8SczmFE0\"", "id": "Ugwa4QlE6No2OVeYkBt4AaABAg", "snippet": {"videoId": "b-TCwqlx2fg", "topLevelComment": {"kind": "youtube#comment", "etag": "\"p4VTdlkQv3HQeTEaXgvLePAydmU/3sL4oP45TjcTvOg9pwfBH1_qmz4\"", "id": "Ugwa4QlE6No2OVeYkBt4AaABAg", "snippet": {"authorDisplayName": "TeaAtTwo", "authorProfileImageUrl": "https://yt3.ggpht.com/a/AGF-l7-EO1Pbx0655YspWwBwQ-eb65dzrNnE8Cg0Bg=s48-c-k-c0xffffffff-no-rj-mo", "authorChannelUrl": "http://www.youtube.com/channel/UCLfvMWMsjt1EeU9Jg0vRO7Q", "authorChannelId": {"value": "UCLfvMWMsjt1EeU9Jg0vRO7Q"}, "videoId": "b-TCwqlx2fg", "textDisplay": "I find Daisy Ridley irritating now after her whole ignorant privilege denial.", "textOriginal": "I find Daisy Ridley irritating now after her whole ignorant privilege denial.", "canRate": true, "viewerRating": "none", "likeCount": 0, "publishedAt": "2019-12-26T09:02:01.000Z", "updatedAt": "2019-12-26T09:02:01.000Z"}}, "canReply": true, "totalReplyCount": 0, "isPublic": true}}, {"kind": "youtube#commentThread", "etag": "\"p4VTdlkQv3HQeTEaXgvLePAydmU/6DKRM4m7cEIF3bIHRunytCBTNJg\"", "id": "UgyBmSrmYXxPBkVWxXd4AaABAg", "snippet": {"videoId": "b-TCwqlx2fg", "topLevelComment": {"kind": "youtube#comment", "etag": "\"p4VTdlkQv3HQeTEaXgvLePAydmU/Di2thR8N0jWyDXyqr_NAcqWkoic\"", "id": "UgyBmSrmYXxPBkVWxXd4AaABAg", "snippet": {"authorDisplayName": "Carolyn's Reading Ramblings", "authorProfileImageUrl": "https://yt3.ggpht.com/a/AGF-l79Ysh5wSCqyglPjbMH_Du66Ut0bItY-Bs13=s48-c-k-c0xffffffff-no-rj-mo", "authorChannelUrl": "http://www.youtube.com/channel/UClFw_6TBouvufUt-_WqGj2w", "authorChannelId": {"value": "UClFw_6TBouvufUt-_WqGj2w"}, "videoId": "b-TCwqlx2fg", "textDisplay": "I about cried laughing at this, both are brilliant but ESPECIALLY Ruth as Nessa Leia \ud83d\ude06\u2764\ufe0f!", "textOriginal": "I about cried laughing at this, both are brilliant but ESPECIALLY Ruth as Nessa Leia \ud83d\ude06\u2764\ufe0f!", "canRate": true, "viewerRating": "none", "likeCount": 0, "publishedAt": "2019-12-25T12:47:37.000Z", "updatedAt": "2019-12-25T12:47:37.000Z"}}, "canReply": true, "totalReplyCount": 0, "isPublic": true}}, {"kind": "youtube#commentThread", "etag": "\"p4VTdlkQv3HQeTEaXgvLePAydmU/LrtaDwHEBkfWpWkuMP8rrNVmhvg\"", "id": "UgyyYshaFBTpLHwWnrF4AaABAg", "snippet": {"videoId": "b-TCwqlx2fg", "topLevelComment": {"kind": "youtube#comment", "etag": "\"p4VTdlkQv3HQeTEaXgvLePAydmU/I4GxkQDoD3kFEsLIH5ublo57k18\"", "id": "UgyyYshaFBTpLHwWnrF4AaABAg", "snippet": {"authorDisplayName": "Joe Wehry", "authorProfileImageUrl": "https://yt3.ggpht.com/a/AGF-l79bGtcGVH-PrPENqFuZNPCMXjL2d0QXn2NSyw=s48-c-k-c0xffffffff-no-rj-mo", "authorChannelUrl": "http://www.youtube.com/channel/UCPFbxlS-i_eLyawjT6BStbQ", "authorChannelId": {"value": "UCPFbxlS-i_eLyawjT6BStbQ"}, "videoId": "b-TCwqlx2fg", "textDisplay": "This is great. I wish these two would actually do a Star Wars movie. It&#39;d be the best in the franchise.", "textOriginal": "This is great. I wish these two would actually do a Star Wars movie. It'd be the best in the franchise.", "canRate": true, "viewerRating": "none", "likeCount": 0, "publishedAt": "2019-12-24T17:17:08.000Z", "updatedAt": "2019-12-24T17:17:08.000Z"}}, "canReply": true, "totalReplyCount": 0, "isPublic": true}}, {"kind": "youtube#commentThread", "etag": "\"p4VTdlkQv3HQeTEaXgvLePAydmU/-0sQgYIAjogU3X3eVY4oYmBq6bQ\"", "id": "Ugw61VgtSD5wvrA2LDR4AaABAg", "snippet": {"videoId": "b-TCwqlx2fg", "topLevelComment": {"kind": "youtube#comment", "etag": "\"p4VTdlkQv3HQeTEaXgvLePAydmU/FOS39HPoyibdMK6EZrW8Qdk2SUA\"", "id": "Ugw61VgtSD5wvrA2LDR4AaABAg", "snippet": {"authorDisplayName": "Mankeerat Singh", "authorProfileImageUrl": "https://yt3.ggpht.com/a/AGF-l799DgLGG1GX7AFIsfK_Vq__2vQ_9JSayJXiCQ=s48-c-k-c0xffffffff-no-rj-mo", "authorChannelUrl": "http://www.youtube.com/channel/UCExXHy7eMlpy0gcDxuUkA6g", "authorChannelId": {"value": "UCExXHy7eMlpy0gcDxuUkA6g"}, "videoId": "b-TCwqlx2fg", "textDisplay": "What happened? I was too busy staring at Daisy.", "textOriginal": "What happened? I was too busy staring at Daisy.", "canRate": true, "viewerRating": "none", "likeCount": 0, "publishedAt": "2019-12-24T12:38:09.000Z", "updatedAt": "2019-12-24T12:38:09.000Z"}}, "canReply": true, "totalReplyCount": 1, "isPublic": true}}, {"kind": "youtube#commentThread", "etag": "\"p4VTdlkQv3HQeTEaXgvLePAydmU/GTQXE04CTaFs_1V3UxUQmNh8F0w\"", "id": "Ugwj7mEt-0lW5L98l2B4AaABAg", "snippet": {"videoId": "b-TCwqlx2fg", "topLevelComment": {"kind": "youtube#comment", "etag": "\"p4VTdlkQv3HQeTEaXgvLePAydmU/RRJ7zKzhnFLdHe2rRn7JFFfDv8A\"", "id": "Ugwj7mEt-0lW5L98l2B4AaABAg", "snippet": {"authorDisplayName": "Mochi's Game Hut", "authorProfileImageUrl": "https://yt3.ggpht.com/a/AGF-l79M4yBJ90hAcx6mrfhnCD94ndwS4kRFNr6oVg=s48-c-k-c0xffffffff-no-rj-mo", "authorChannelUrl": "http://www.youtube.com/channel/UCcLm3anuDkqw3eX-uTBfLiA", "authorChannelId": {"value": "UCcLm3anuDkqw3eX-uTBfLiA"}, "videoId": "b-TCwqlx2fg", "textDisplay": "I like how it says Daisy Ridley watches, yet it barely ever shows her.", "textOriginal": "I like how it says Daisy Ridley watches, yet it barely ever shows her.", "canRate": true, "viewerRating": "none", "likeCount": 1, "publishedAt": "2019-12-24T11:17:00.000Z", "updatedAt": "2019-12-24T11:17:00.000Z"}}, "canReply": true, "totalReplyCount": 0, "isPublic": true}}, {"kind": "youtube#commentThread", "etag": "\"p4VTdlkQv3HQeTEaXgvLePAydmU/I2mn6MPnIurmVWWOZvpS7BzwoZo\"", "id": "UgywUrhbEIX3BLeZ0A54AaABAg", "snippet": {"videoId": "b-TCwqlx2fg", "topLevelComment": {"kind": "youtube#comment", "etag": "\"p4VTdlkQv3HQeTEaXgvLePAydmU/yJnpA3sjOzUPb3l2eYQapgeDZDA\"", "id": "UgywUrhbEIX3BLeZ0A54AaABAg", "snippet": {"authorDisplayName": "xoobo vola", "authorProfileImageUrl": "https://yt3.ggpht.com/a/AGF-l78Q9jpw2Or2p3J7v050dHFmZXNvQqisOdm_og=s48-c-k-c0xffffffff-no-rj-mo", "authorChannelUrl": "http://www.youtube.com/channel/UCrSHSHW9yUvUjshxmLfsNjw", "authorChannelId": {"value": "UCrSHSHW9yUvUjshxmLfsNjw"}, "videoId": "b-TCwqlx2fg", "textDisplay": "Yaay", "textOriginal": "Yaay", "canRate": true, "viewerRating": "none", "likeCount": 0, "publishedAt": "2019-12-24T06:07:58.000Z", "updatedAt": "2019-12-24T06:07:58.000Z"}}, "canReply": true, "totalReplyCount": 1, "isPublic": true}}, {"kind": "youtube#commentThread", "etag": "\"p4VTdlkQv3HQeTEaXgvLePAydmU/kPI67Zd5a8gOOu0KLQikIuNxUaQ\"", "id": "Ugz9iOOxYERQAkDREkd4AaABAg", "snippet": {"videoId": "b-TCwqlx2fg", "topLevelComment": {"kind": "youtube#comment", "etag": "\"p4VTdlkQv3HQeTEaXgvLePAydmU/aiJp8JTiPxCQ2J8iDL5r9G0QoLA\"", "id": "Ugz9iOOxYERQAkDREkd4AaABAg", "snippet": {"authorDisplayName": "aola wili", "authorProfileImageUrl": "https://yt3.ggpht.com/a/AGF-l7_LhLKsyNFxY9AJfjb37A0BZAcbP_MYILR5XA=s48-c-k-c0xffffffff-no-rj-mo", "authorChannelUrl": "http://www.youtube.com/channel/UCMB1QJxQ6FDI_SF6YVgoTrQ", "authorChannelId": {"value": "UCMB1QJxQ6FDI_SF6YVgoTrQ"}, "videoId": "b-TCwqlx2fg", "textDisplay": "&quot;You had your chance, you never took it&quot;", "textOriginal": "\"You had your chance, you never took it\"", "canRate": true, "viewerRating": "none", "likeCount": 0, "publishedAt": "2019-12-24T00:52:28.000Z", "updatedAt": "2019-12-24T00:52:28.000Z"}}, "canReply": true, "totalReplyCount": 1, "isPublic": true}}, {"kind": "youtube#commentThread", "etag": "\"p4VTdlkQv3HQeTEaXgvLePAydmU/J928PvJ2Jw59-96uKyA1ho_TKG4\"", "id": "Ugzb5cq93Y1VLqXupBd4AaABAg", "snippet": {"videoId": "b-TCwqlx2fg", "topLevelComment": {"kind": "youtube#comment", "etag": "\"p4VTdlkQv3HQeTEaXgvLePAydmU/lkyaKEayUS1VAAxDa7CxcbDXeLI\"", "id": "Ugzb5cq93Y1VLqXupBd4AaABAg", "snippet": {"authorDisplayName": "okow tina", "authorProfileImageUrl": "https://yt3.ggpht.com/a/AGF-l79faPZIn0Nq_drUyTmBLkNIJqr4WSUQEk1h_Q=s48-c-k-c0xffffffff-no-rj-mo", "authorChannelUrl": "http://www.youtube.com/channel/UCbnWGuUC6XcCqstIw9xZCPw", "authorChannelId": {"value": "UCbnWGuUC6XcCqstIw9xZCPw"}, "videoId": "b-TCwqlx2fg", "textDisplay": "&quot;You had your chance, you never took it&quot;", "textOriginal": "\"You had your chance, you never took it\"", "canRate": true, "viewerRating": "none", "likeCount": 0, "publishedAt": "2019-12-23T20:02:09.000Z", "updatedAt": "2019-12-23T20:02:09.000Z"}}, "canReply": true, "totalReplyCount": 1, "isPublic": true}}, {"kind": "youtube#commentThread", "etag": "\"p4VTdlkQv3HQeTEaXgvLePAydmU/I26m2WbRKGsBsBb3BNAhQyyhsMY\"", "id": "UgxV3BUQiVSof0Cd2ZV4AaABAg", "snippet": {"videoId": "b-TCwqlx2fg", "topLevelComment": {"kind": "youtube#comment", "etag": "\"p4VTdlkQv3HQeTEaXgvLePAydmU/QxfnwLu1_epnvpL6tK_CvYOos3Q\"", "id": "UgxV3BUQiVSof0Cd2ZV4AaABAg", "snippet": {"authorDisplayName": "MarielIsabel", "authorProfileImageUrl": "https://yt3.ggpht.com/a/AGF-l7_BKHzV2FYOQBeZekFslJW6ECipLrKgcKZm=s48-c-k-c0xffffffff-no-rj-mo", "authorChannelUrl": "http://www.youtube.com/channel/UCOZqat3eJO7Ukk0pV-XWLNg", "authorChannelId": {"value": "UCOZqat3eJO7Ukk0pV-XWLNg"}, "videoId": "b-TCwqlx2fg", "textDisplay": "Love this so much", "textOriginal": "Love this so much", "canRate": true, "viewerRating": "none", "likeCount": 0, "publishedAt": "2019-12-23T19:08:46.000Z", "updatedAt": "2019-12-23T19:08:46.000Z"}}, "canReply": true, "totalReplyCount": 1, "isPublic": true}}, {"kind": "youtube#commentThread", "etag": "\"p4VTdlkQv3HQeTEaXgvLePAydmU/4ObqJ-MEWf0XL_-dIUV1TSMWpw4\"", "id": "UgyFx8oCftjyEIX27HJ4AaABAg", "snippet": {"videoId": "b-TCwqlx2fg", "topLevelComment": {"kind": "youtube#comment", "etag": "\"p4VTdlkQv3HQeTEaXgvLePAydmU/sV3jBs780q02zxMWDdwgylqjP2k\"", "id": "UgyFx8oCftjyEIX27HJ4AaABAg", "snippet": {"authorDisplayName": "Shauka Hodan", "authorProfileImageUrl": "https://yt3.ggpht.com/a/AGF-l79qHUaAVK5G8WozkH5oRm2p7BcbgqrL-z9CSw=s48-c-k-c0xffffffff-no-rj-mo", "authorChannelUrl": "http://www.youtube.com/channel/UCIxcUIVjTK-IyCQEhfyI4JA", "authorChannelId": {"value": "UCIxcUIVjTK-IyCQEhfyI4JA"}, "videoId": "b-TCwqlx2fg", "textDisplay": "God, please don&#39;t make me comment!", "textOriginal": "God, please don't make me comment!", "canRate": true, "viewerRating": "none", "likeCount": 0, "publishedAt": "2019-12-23T15:06:07.000Z", "updatedAt": "2019-12-23T15:06:07.000Z"}}, "canReply": true, "totalReplyCount": 1, "isPublic": true}}, {"kind": "youtube#commentThread", "etag": "\"p4VTdlkQv3HQeTEaXgvLePAydmU/S7JomIfEm-RqjqpDHjr163L0Qj4\"", "id": "UgyS6zzkF6zZPpALJjN4AaABAg", "snippet": {"videoId": "b-TCwqlx2fg", "topLevelComment": {"kind": "youtube#comment", "etag": "\"p4VTdlkQv3HQeTEaXgvLePAydmU/XMCoruM6hWQ_RTCpqedmGF7Bag4\"", "id": "UgyS6zzkF6zZPpALJjN4AaABAg", "snippet": {"authorDisplayName": "Deeplays Gaming", "authorProfileImageUrl": "https://yt3.ggpht.com/a/AGF-l7-kpS435LsCWfNUt7HYZWOfWSHcRwuyB1A15Q=s48-c-k-c0xffffffff-no-rj-mo", "authorChannelUrl": "http://www.youtube.com/channel/UCKFcOo18vn5KgN2OvCdUsww", "authorChannelId": {"value": "UCKFcOo18vn5KgN2OvCdUsww"}, "videoId": "b-TCwqlx2fg", "textDisplay": "great!!!! now do avengers endgame thanos tony stark speech.", "textOriginal": "great!!!! now do avengers endgame thanos tony stark speech.", "canRate": true, "viewerRating": "none", "likeCount": 0, "publishedAt": "2019-12-23T09:00:41.000Z", "updatedAt": "2019-12-23T09:00:41.000Z"}}, "canReply": true, "totalReplyCount": 1, "isPublic": true}}, {"kind": "youtube#commentThread", "etag": "\"p4VTdlkQv3HQeTEaXgvLePAydmU/7p9SzMbnMg0WiId8oPilJToozoQ\"", "id": "UgzzAMvepuwvMEK-k2Z4AaABAg", "snippet": {"videoId": "b-TCwqlx2fg", "topLevelComment": {"kind": "youtube#comment", "etag": "\"p4VTdlkQv3HQeTEaXgvLePAydmU/TK6EzKmbdVhHRqDKACzZ6culrhM\"", "id": "UgzzAMvepuwvMEK-k2Z4AaABAg", "snippet": {"authorDisplayName": "yroohj gouy", "authorProfileImageUrl": "https://yt3.ggpht.com/a/AGF-l7_BmloCYCKEUpV9HMrQRMrUs6I03ymv7bacoQ=s48-c-k-c0xffffffff-no-rj-mo", "authorChannelUrl": "http://www.youtube.com/channel/UCmwYA8kSu6IROn2KMokuegw", "authorChannelId": {"value": "UCmwYA8kSu6IROn2KMokuegw"}, "videoId": "b-TCwqlx2fg", "textDisplay": "&quot;You had your chance, you never took it&quot;", "textOriginal": "\"You had your chance, you never took it\"", "canRate": true, "viewerRating": "none", "likeCount": 2, "publishedAt": "2019-12-22T23:46:25.000Z", "updatedAt": "2019-12-22T23:46:25.000Z"}}, "canReply": true, "totalReplyCount": 0, "isPublic": true}}, {"kind": "youtube#commentThread", "etag": "\"p4VTdlkQv3HQeTEaXgvLePAydmU/-_eFrTmWsCj2Gb1v8x7FArwHH20\"", "id": "UgxOWgBEhEhYR0_Gf014AaABAg", "snippet": {"videoId": "b-TCwqlx2fg", "topLevelComment": {"kind": "youtube#comment", "etag": "\"p4VTdlkQv3HQeTEaXgvLePAydmU/AcvgVqYmDo_NvVQ8rDY2Q0H8yUI\"", "id": "UgxOWgBEhEhYR0_Gf014AaABAg", "snippet": {"authorDisplayName": "Alana Gorman", "authorProfileImageUrl": "https://yt3.ggpht.com/a/AGF-l7_sotzAYeG6vamwdhzM6Tl_8FFm6NiamqykBA=s48-c-k-c0xffffffff-no-rj-mo", "authorChannelUrl": "http://www.youtube.com/channel/UCCIFMmV_NHIkk2sMYsww54w", "authorChannelId": {"value": "UCCIFMmV_NHIkk2sMYsww54w"}, "videoId": "b-TCwqlx2fg", "textDisplay": "I was in stitches watching this \ud83d\ude02", "textOriginal": "I was in stitches watching this \ud83d\ude02", "canRate": true, "viewerRating": "none", "likeCount": 2, "publishedAt": "2019-12-22T22:21:03.000Z", "updatedAt": "2019-12-22T22:21:03.000Z"}}, "canReply": true, "totalReplyCount": 1, "isPublic": true}}, {"kind": "youtube#commentThread", "etag": "\"p4VTdlkQv3HQeTEaXgvLePAydmU/8b30_TjSzaFcZJs6HaLmSftAm7A\"", "id": "UgyCSkhmgU8ySVs-Omp4AaABAg", "snippet": {"videoId": "b-TCwqlx2fg", "topLevelComment": {"kind": "youtube#comment", "etag": "\"p4VTdlkQv3HQeTEaXgvLePAydmU/1hY9UMXS0U6-YeDaf5rxyLlOKG0\"", "id": "UgyCSkhmgU8ySVs-Omp4AaABAg", "snippet": {"authorDisplayName": "Scott B", "authorProfileImageUrl": "https://yt3.ggpht.com/a/AGF-l79GIy9M6UvTz2ElzQ2yJrPN1ZgoxQcYGOZEhQ=s48-c-k-c0xffffffff-no-rj-mo", "authorChannelUrl": "http://www.youtube.com/channel/UCrqumMTVryHOPeJPTNFSFiQ", "authorChannelId": {"value": "UCrqumMTVryHOPeJPTNFSFiQ"}, "videoId": "b-TCwqlx2fg", "textDisplay": "Felt sorry for Henry, Gave literally zero plug time for The Witcher!", "textOriginal": "Felt sorry for Henry, Gave literally zero plug time for The Witcher!", "canRate": true, "viewerRating": "none", "likeCount": 0, "publishedAt": "2019-12-22T19:32:06.000Z", "updatedAt": "2019-12-22T19:32:06.000Z"}}, "canReply": true, "totalReplyCount": 2, "isPublic": true}}, {"kind": "youtube#commentThread", "etag": "\"p4VTdlkQv3HQeTEaXgvLePAydmU/Rr3uBE7_CAykToxVYQ68qy_AO54\"", "id": "UgwIsCrEuFaB_hWMKG54AaABAg", "snippet": {"videoId": "b-TCwqlx2fg", "topLevelComment": {"kind": "youtube#comment", "etag": "\"p4VTdlkQv3HQeTEaXgvLePAydmU/IAgpnGhKbZCNUhrKVHY18s45KeE\"", "id": "UgwIsCrEuFaB_hWMKG54AaABAg", "snippet": {"authorDisplayName": "STempaz 90", "authorProfileImageUrl": "https://yt3.ggpht.com/a/AGF-l7_CnKB016nbK4rggfZem7qhDJp-M5bluiSaVA=s48-c-k-c0xffffffff-no-rj-mo", "authorChannelUrl": "http://www.youtube.com/channel/UC5Qluy7BBMM1FEp-zhnaXNw", "authorChannelId": {"value": "UC5Qluy7BBMM1FEp-zhnaXNw"}, "videoId": "b-TCwqlx2fg", "textDisplay": "I have a great idea for a movie starring Henry Cavill and Daisy Ridley. They play cousins, his name is Clark and hers is Kara.", "textOriginal": "I have a great idea for a movie starring Henry Cavill and Daisy Ridley. They play cousins, his name is Clark and hers is Kara.", "canRate": true, "viewerRating": "none", "likeCount": 7, "publishedAt": "2019-12-22T19:24:22.000Z", "updatedAt": "2019-12-22T19:24:22.000Z"}}, "canReply": true, "totalReplyCount": 1, "isPublic": true}}, {"kind": "youtube#commentThread", "etag": "\"p4VTdlkQv3HQeTEaXgvLePAydmU/nHhm3wwlt2Fyksole7KywcFZpKE\"", "id": "UgyV-nUH3nqBnVaLECR4AaABAg", "snippet": {"videoId": "b-TCwqlx2fg", "topLevelComment": {"kind": "youtube#comment", "etag": "\"p4VTdlkQv3HQeTEaXgvLePAydmU/JFZB3jP_02DPVyILPHx_A6gYuqA\"", "id": "UgyV-nUH3nqBnVaLECR4AaABAg", "snippet": {"authorDisplayName": "neejoy sola", "authorProfileImageUrl": "https://yt3.ggpht.com/a/AGF-l79QoynSi1cugQ62_q4qmr-1Un0h6OxmmqUpUA=s48-c-k-c0xffffffff-no-rj-mo", "authorChannelUrl": "http://www.youtube.com/channel/UC8p52VVmLWSMh-uqZHRq3Nw", "authorChannelId": {"value": "UC8p52VVmLWSMh-uqZHRq3Nw"}, "videoId": "b-TCwqlx2fg", "textDisplay": "God, please don&#39;t make me comment!", "textOriginal": "God, please don't make me comment!", "canRate": true, "viewerRating": "none", "likeCount": 0, "publishedAt": "2019-12-22T19:03:03.000Z", "updatedAt": "2019-12-22T19:03:03.000Z"}}, "canReply": true, "totalReplyCount": 1, "isPublic": true}}, {"kind": "youtube#commentThread", "etag": "\"p4VTdlkQv3HQeTEaXgvLePAydmU/KM-_TTKzGjDa7pjguLmKSXCmocI\"", "id": "UgyjH-rYJrpTPp_ieh94AaABAg", "snippet": {"videoId": "b-TCwqlx2fg", "topLevelComment": {"kind": "youtube#comment", "etag": "\"p4VTdlkQv3HQeTEaXgvLePAydmU/GQ14bRGeq6CMeCTI5UkTqDlPN4Y\"", "id": "UgyjH-rYJrpTPp_ieh94AaABAg", "snippet": {"authorDisplayName": "JoAnn Hauser", "authorProfileImageUrl": "https://yt3.ggpht.com/a/AGF-l79Da83MXeqMi4gIBsx52XN_iU7gJBLS34mX1w=s48-c-k-c0xffffffff-no-rj-mo", "authorChannelUrl": "http://www.youtube.com/channel/UClIDKZZ-XvW3AojZtKxwiQg", "authorChannelId": {"value": "UClIDKZZ-XvW3AojZtKxwiQg"}, "videoId": "b-TCwqlx2fg", "textDisplay": "Graham you look gorgeous in all the Christmas episodes!!!\ud83d\ude18\ud83e\udd73\ud83e\udd17", "textOriginal": "Graham you look gorgeous in all the Christmas episodes!!!\ud83d\ude18\ud83e\udd73\ud83e\udd17", "canRate": true, "viewerRating": "none", "likeCount": 0, "publishedAt": "2019-12-22T18:24:47.000Z", "updatedAt": "2019-12-22T18:24:47.000Z"}}, "canReply": true, "totalReplyCount": 0, "isPublic": true}}]