[{"kind": "youtube#commentThread", "etag": "\"p4VTdlkQv3HQeTEaXgvLePAydmU/1MfN8XfYY0hcMn3EerWe-1v_9L8\"", "id": "UgyQIP8BP4JGhBTAIDJ4AaABAg", "snippet": {"videoId": "wDTX2ntqTmo", "topLevelComment": {"kind": "youtube#comment", "etag": "\"p4VTdlkQv3HQeTEaXgvLePAydmU/c-c8VtoZ04ggT45wfN6HsU9IZfw\"", "id": "UgyQIP8BP4JGhBTAIDJ4AaABAg", "snippet": {"authorDisplayName": "Robert The Great", "authorProfileImageUrl": "https://yt3.ggpht.com/a/AGF-l7-aAMfvIMu5_qcoIm4w1rIM4VtOiQQ0Mu7qJA=s48-c-k-c0xffffffff-no-rj-mo", "authorChannelUrl": "http://www.youtube.com/channel/UCQyFVKWCa0xvkRTGix_eHQg", "authorChannelId": {"value": "UCQyFVKWCa0xvkRTGix_eHQg"}, "videoId": "wDTX2ntqTmo", "textDisplay": "Ruiz vs Wilder <br />Dana White make it happen!", "textOriginal": "Ruiz vs Wilder \nDana White make it happen!", "canRate": true, "viewerRating": "none", "likeCount": 0, "publishedAt": "2019-12-24T05:52:52.000Z", "updatedAt": "2019-12-24T05:52:52.000Z"}}, "canReply": true, "totalReplyCount": 0, "isPublic": true}}, {"kind": "youtube#commentThread", "etag": "\"p4VTdlkQv3HQeTEaXgvLePAydmU/Ajx31gOH_RUZglkTLZZPbr8-TR8\"", "id": "UgwAG38yDSmczuFlJo54AaABAg", "snippet": {"videoId": "wDTX2ntqTmo", "topLevelComment": {"kind": "youtube#comment", "etag": "\"p4VTdlkQv3HQeTEaXgvLePAydmU/v76YiJrqSjD79KY3PxSouLnssGM\"", "id": "UgwAG38yDSmczuFlJo54AaABAg", "snippet": {"authorDisplayName": "Tony254Texas", "authorProfileImageUrl": "https://yt3.ggpht.com/a/AGF-l79qNmH7JFG7dDF9UGnlh0Sn0CTPL_s79WrMgQ=s48-c-k-c0xffffffff-no-rj-mo", "authorChannelUrl": "http://www.youtube.com/channel/UCYbud2oRly-WMMLWZz5lgQw", "authorChannelId": {"value": "UCYbud2oRly-WMMLWZz5lgQw"}, "videoId": "wDTX2ntqTmo", "textDisplay": "Fury and AJ is the fight I wanna see the most. Wilder has insane power but I\u2019m a boxing purist fan", "textOriginal": "Fury and AJ is the fight I wanna see the most. Wilder has insane power but I\u2019m a boxing purist fan", "canRate": true, "viewerRating": "none", "likeCount": 0, "publishedAt": "2019-12-22T08:16:35.000Z", "updatedAt": "2019-12-22T08:16:35.000Z"}}, "canReply": true, "totalReplyCount": 0, "isPublic": true}}, {"kind": "youtube#commentThread", "etag": "\"p4VTdlkQv3HQeTEaXgvLePAydmU/VmQBR7B_pH6LTvJweMxEUCyMGX8\"", "id": "UgwX_KS6qF_QIMGwBy94AaABAg", "snippet": {"videoId": "wDTX2ntqTmo", "topLevelComment": {"kind": "youtube#comment", "etag": "\"p4VTdlkQv3HQeTEaXgvLePAydmU/a5hqRLk1syFP59I6itWNZKBGDYw\"", "id": "UgwX_KS6qF_QIMGwBy94AaABAg", "snippet": {"authorDisplayName": "bilishu aliss", "authorProfileImageUrl": "https://yt3.ggpht.com/a/AGF-l7_cMsQ9Hk9LmpkyrJX-sFQULak3b6qFPCRzyw=s48-c-k-c0xffffffff-no-rj-mo", "authorChannelUrl": "http://www.youtube.com/channel/UCt9YOoa4OLzQCBLedrslAeA", "authorChannelId": {"value": "UCt9YOoa4OLzQCBLedrslAeA"}, "videoId": "wDTX2ntqTmo", "textDisplay": "Eddie &quot;I spoke to Ajs mum last night&quot; Hearn", "textOriginal": "Eddie \"I spoke to Ajs mum last night\" Hearn", "canRate": true, "viewerRating": "none", "likeCount": 1, "publishedAt": "2019-12-22T03:21:14.000Z", "updatedAt": "2019-12-22T03:21:14.000Z"}}, "canReply": true, "totalReplyCount": 0, "isPublic": true}}, {"kind": "youtube#commentThread", "etag": "\"p4VTdlkQv3HQeTEaXgvLePAydmU/7Cp1jZ3CuN0fhXXC61_ihBZvKhk\"", "id": "UgxODiWWIS27CLyS0wp4AaABAg", "snippet": {"videoId": "wDTX2ntqTmo", "topLevelComment": {"kind": "youtube#comment", "etag": "\"p4VTdlkQv3HQeTEaXgvLePAydmU/0O40YGNpFjNToEmzx5IdTZob-Hg\"", "id": "UgxODiWWIS27CLyS0wp4AaABAg", "snippet": {"authorDisplayName": "neejoy sola", "authorProfileImageUrl": "https://yt3.ggpht.com/a/AGF-l79QoynSi1cugQ62_q4qmr-1Un0h6OxmmqUpUA=s48-c-k-c0xffffffff-no-rj-mo", "authorChannelUrl": "http://www.youtube.com/channel/UC8p52VVmLWSMh-uqZHRq3Nw", "authorChannelId": {"value": "UC8p52VVmLWSMh-uqZHRq3Nw"}, "videoId": "wDTX2ntqTmo", "textDisplay": "Eddie could convince me it\u2019s a good idea to sleep with my missus and I would believe him", "textOriginal": "Eddie could convince me it\u2019s a good idea to sleep with my missus and I would believe him", "canRate": true, "viewerRating": "none", "likeCount": 0, "publishedAt": "2019-12-21T16:18:47.000Z", "updatedAt": "2019-12-21T16:18:47.000Z"}}, "canReply": true, "totalReplyCount": 0, "isPublic": true}}, {"kind": "youtube#commentThread", "etag": "\"p4VTdlkQv3HQeTEaXgvLePAydmU/JguiuZqQmtRkvAVbXIeCGvTL8NQ\"", "id": "UgxHSPzxQOLEWo7C88d4AaABAg", "snippet": {"videoId": "wDTX2ntqTmo", "topLevelComment": {"kind": "youtube#comment", "etag": "\"p4VTdlkQv3HQeTEaXgvLePAydmU/GhEJvzvtPa5eNWPRD1XnRmImnLE\"", "id": "UgxHSPzxQOLEWo7C88d4AaABAg", "snippet": {"authorDisplayName": "Patrick Kennedy", "authorProfileImageUrl": "https://yt3.ggpht.com/a/AGF-l78rXAAcIIhgsc4dfI9ZtaxEz2O_bQjPfe_V8Q=s48-c-k-c0xffffffff-no-rj-mo", "authorChannelUrl": "http://www.youtube.com/channel/UCyN5dr8jL-vIlcawNednUxg", "authorChannelId": {"value": "UCyN5dr8jL-vIlcawNednUxg"}, "videoId": "wDTX2ntqTmo", "textDisplay": "For such a huge fight Fury vs AJ could be the most boring fight ever. Win at any cost is the mindset, the Mayweather blue-print one or two decent punches in the entire fight!", "textOriginal": "For such a huge fight Fury vs AJ could be the most boring fight ever. Win at any cost is the mindset, the Mayweather blue-print one or two decent punches in the entire fight!", "canRate": true, "viewerRating": "none", "likeCount": 0, "publishedAt": "2019-12-21T15:55:40.000Z", "updatedAt": "2019-12-21T15:55:40.000Z"}}, "canReply": true, "totalReplyCount": 0, "isPublic": true}}, {"kind": "youtube#commentThread", "etag": "\"p4VTdlkQv3HQeTEaXgvLePAydmU/P0eaNhnVtcSxVACSWq669-dt7m8\"", "id": "UgyVmyGrVFVRGzEmUPR4AaABAg", "snippet": {"videoId": "wDTX2ntqTmo", "topLevelComment": {"kind": "youtube#comment", "etag": "\"p4VTdlkQv3HQeTEaXgvLePAydmU/lh5cJMQ8oEa08Xx0XSvKQqeo8RI\"", "id": "UgyVmyGrVFVRGzEmUPR4AaABAg", "snippet": {"authorDisplayName": "Robbie Bailey", "authorProfileImageUrl": "https://yt3.ggpht.com/a/AGF-l79RSk_GQXs7Z0z7Ii9hzbxQ899NU2dVI3upSA=s48-c-k-c0xffffffff-no-rj-mo", "authorChannelUrl": "http://www.youtube.com/channel/UC_mVnPz9LgGJqBiCuXdBtRw", "authorChannelId": {"value": "UC_mVnPz9LgGJqBiCuXdBtRw"}, "videoId": "wDTX2ntqTmo", "textDisplay": "Joshua V Pulev WBA/IBF/IBO<br />Usyk V Whyte WBO<br /><br />Then winners face eachother would be decent", "textOriginal": "Joshua V Pulev WBA/IBF/IBO\nUsyk V Whyte WBO\n\nThen winners face eachother would be decent", "canRate": true, "viewerRating": "none", "likeCount": 0, "publishedAt": "2019-12-21T14:40:46.000Z", "updatedAt": "2019-12-21T14:40:46.000Z"}}, "canReply": true, "totalReplyCount": 1, "isPublic": true}}, {"kind": "youtube#commentThread", "etag": "\"p4VTdlkQv3HQeTEaXgvLePAydmU/lWTQrTX7gJK9BtnFTiXxtPyAK2k\"", "id": "Ugw52mrA1ZFyCP5gXJh4AaABAg", "snippet": {"videoId": "wDTX2ntqTmo", "topLevelComment": {"kind": "youtube#comment", "etag": "\"p4VTdlkQv3HQeTEaXgvLePAydmU/2RUl2f61Y7hIg70hDrgAUdSgZqw\"", "id": "Ugw52mrA1ZFyCP5gXJh4AaABAg", "snippet": {"authorDisplayName": "Shaggy", "authorProfileImageUrl": "https://yt3.ggpht.com/a/AGF-l7-VlpKgx2UmNfVP7Ye_Y4uAcIRp_0HqaHMYtw=s48-c-k-c0xffffffff-no-rj-mo", "authorChannelUrl": "http://www.youtube.com/channel/UC9KP83-WBgXZbR0ucW0T92A", "authorChannelId": {"value": "UC9KP83-WBgXZbR0ucW0T92A"}, "videoId": "wDTX2ntqTmo", "textDisplay": "Stop ducking AJ vs Fury or AJ Vs Wilder nobody wants hear about same fight FRAUD.!!!", "textOriginal": "Stop ducking AJ vs Fury or AJ Vs Wilder nobody wants hear about same fight FRAUD.!!!", "canRate": true, "viewerRating": "none", "likeCount": 1, "publishedAt": "2019-12-21T10:55:55.000Z", "updatedAt": "2019-12-21T10:55:55.000Z"}}, "canReply": true, "totalReplyCount": 2, "isPublic": true}}, {"kind": "youtube#commentThread", "etag": "\"p4VTdlkQv3HQeTEaXgvLePAydmU/JM7qqzk-x5LupJWMoiK1pNa2riU\"", "id": "UgyYzWdHzirFc9SHbnh4AaABAg", "snippet": {"videoId": "wDTX2ntqTmo", "topLevelComment": {"kind": "youtube#comment", "etag": "\"p4VTdlkQv3HQeTEaXgvLePAydmU/9hx4LGTIb29Roxn3dyjJtM9R4ww\"", "id": "UgyYzWdHzirFc9SHbnh4AaABAg", "snippet": {"authorDisplayName": "Shaggy", "authorProfileImageUrl": "https://yt3.ggpht.com/a/AGF-l7-VlpKgx2UmNfVP7Ye_Y4uAcIRp_0HqaHMYtw=s48-c-k-c0xffffffff-no-rj-mo", "authorChannelUrl": "http://www.youtube.com/channel/UC9KP83-WBgXZbR0ucW0T92A", "authorChannelId": {"value": "UC9KP83-WBgXZbR0ucW0T92A"}, "videoId": "wDTX2ntqTmo", "textDisplay": "Fraud money prop", "textOriginal": "Fraud money prop", "canRate": true, "viewerRating": "none", "likeCount": 1, "publishedAt": "2019-12-21T10:55:18.000Z", "updatedAt": "2019-12-21T10:55:18.000Z"}}, "canReply": true, "totalReplyCount": 2, "isPublic": true}}, {"kind": "youtube#commentThread", "etag": "\"p4VTdlkQv3HQeTEaXgvLePAydmU/Dco_6zwNu3W36LOkZ9rM9zGiLdE\"", "id": "UgzEmr9QgS7ltKhs0zJ4AaABAg", "snippet": {"videoId": "wDTX2ntqTmo", "topLevelComment": {"kind": "youtube#comment", "etag": "\"p4VTdlkQv3HQeTEaXgvLePAydmU/tKzJtfLLiAJuSmj8MNfOi9QT6PI\"", "id": "UgzEmr9QgS7ltKhs0zJ4AaABAg", "snippet": {"authorDisplayName": "yroohj gouy", "authorProfileImageUrl": "https://yt3.ggpht.com/a/AGF-l7_BmloCYCKEUpV9HMrQRMrUs6I03ymv7bacoQ=s48-c-k-c0xffffffff-no-rj-mo", "authorChannelUrl": "http://www.youtube.com/channel/UCmwYA8kSu6IROn2KMokuegw", "authorChannelId": {"value": "UCmwYA8kSu6IROn2KMokuegw"}, "videoId": "wDTX2ntqTmo", "textDisplay": "Really sick of this intro now", "textOriginal": "Really sick of this intro now", "canRate": true, "viewerRating": "none", "likeCount": 0, "publishedAt": "2019-12-21T10:38:29.000Z", "updatedAt": "2019-12-21T10:38:29.000Z"}}, "canReply": true, "totalReplyCount": 1, "isPublic": true}}, {"kind": "youtube#commentThread", "etag": "\"p4VTdlkQv3HQeTEaXgvLePAydmU/UIE21_hdTkaz3DaCPeiqSomzvsA\"", "id": "UgzoGrXq8WNGlB_AM4h4AaABAg", "snippet": {"videoId": "wDTX2ntqTmo", "topLevelComment": {"kind": "youtube#comment", "etag": "\"p4VTdlkQv3HQeTEaXgvLePAydmU/ijsHYFYcImGKoWkdNx9vWDgJyeY\"", "id": "UgzoGrXq8WNGlB_AM4h4AaABAg", "snippet": {"authorDisplayName": "That\u2019sabitofa weirdanalogy", "authorProfileImageUrl": "https://yt3.ggpht.com/a/AGF-l7-hYf-joqXqxmlej8wo-bf2wtHxlcNMNXo25A=s48-c-k-c0xffffffff-no-rj-mo", "authorChannelUrl": "http://www.youtube.com/channel/UCQCl_ypVOuOG-BUV4ERuDSQ", "authorChannelId": {"value": "UCQCl_ypVOuOG-BUV4ERuDSQ"}, "videoId": "wDTX2ntqTmo", "textDisplay": "Eddie \u201cboxing just exonerates that\u201d Hearn", "textOriginal": "Eddie \u201cboxing just exonerates that\u201d Hearn", "canRate": true, "viewerRating": "none", "likeCount": 0, "publishedAt": "2019-12-21T10:18:37.000Z", "updatedAt": "2019-12-21T10:18:37.000Z"}}, "canReply": true, "totalReplyCount": 0, "isPublic": true}}, {"kind": "youtube#commentThread", "etag": "\"p4VTdlkQv3HQeTEaXgvLePAydmU/mUu3CsVzeRZCsMmusgY5Fhmo5x8\"", "id": "UgwUZFrnlUUWDdwvYKF4AaABAg", "snippet": {"videoId": "wDTX2ntqTmo", "topLevelComment": {"kind": "youtube#comment", "etag": "\"p4VTdlkQv3HQeTEaXgvLePAydmU/oJBTpR5-KzNMmbNDWl0WOsAofvk\"", "id": "UgwUZFrnlUUWDdwvYKF4AaABAg", "snippet": {"authorDisplayName": "okow tina", "authorProfileImageUrl": "https://yt3.ggpht.com/a/AGF-l79faPZIn0Nq_drUyTmBLkNIJqr4WSUQEk1h_Q=s48-c-k-c0xffffffff-no-rj-mo", "authorChannelUrl": "http://www.youtube.com/channel/UCbnWGuUC6XcCqstIw9xZCPw", "authorChannelId": {"value": "UCbnWGuUC6XcCqstIw9xZCPw"}, "videoId": "wDTX2ntqTmo", "textDisplay": "<a href=\"https://www.youtube.com/watch?v=wDTX2ntqTmo&amp;t=5m31s\">5:31</a> carl froch and the other sky team.", "textOriginal": "5:31 carl froch and the other sky team.", "canRate": true, "viewerRating": "none", "likeCount": 0, "publishedAt": "2019-12-21T05:07:36.000Z", "updatedAt": "2019-12-21T05:07:36.000Z"}}, "canReply": true, "totalReplyCount": 0, "isPublic": true}}, {"kind": "youtube#commentThread", "etag": "\"p4VTdlkQv3HQeTEaXgvLePAydmU/u_jp8eBsjb4-0VoUeA-FuLMoriY\"", "id": "Ugw_CE_eiUB0SDpHlt14AaABAg", "snippet": {"videoId": "wDTX2ntqTmo", "topLevelComment": {"kind": "youtube#comment", "etag": "\"p4VTdlkQv3HQeTEaXgvLePAydmU/HX38_xfZz6vi6Fqw2izz-F8lImE\"", "id": "Ugw_CE_eiUB0SDpHlt14AaABAg", "snippet": {"authorDisplayName": "Jhon Famo", "authorProfileImageUrl": "https://yt3.ggpht.com/a/AGF-l790AXQtKsqrbNL3AxJ0djEa7NoMBy2VoSD8Pg=s48-c-k-c0xffffffff-no-rj-mo", "authorChannelUrl": "http://www.youtube.com/channel/UCGDKhxKL0yV5RXSSYUiLNjw", "authorChannelId": {"value": "UCGDKhxKL0yV5RXSSYUiLNjw"}, "videoId": "wDTX2ntqTmo", "textDisplay": "When Eddie admit &quot; it&#39;s easier not to have belts&quot; take notes haters. People relinquish belts because in a very dangerous sport...the pros do it for the MONEY. fuck the clown boxing channels that judge these fighters\ud83d\ude10\ud83d\ude11\ud83d\ude02\ud83d\ude02\ud83d\ude02\ud83d\ude02\ud83d\ude18", "textOriginal": "When Eddie admit \" it's easier not to have belts\" take notes haters. People relinquish belts because in a very dangerous sport...the pros do it for the MONEY. fuck the clown boxing channels that judge these fighters\ud83d\ude10\ud83d\ude11\ud83d\ude02\ud83d\ude02\ud83d\ude02\ud83d\ude02\ud83d\ude18", "canRate": true, "viewerRating": "none", "likeCount": 0, "publishedAt": "2019-12-20T23:47:13.000Z", "updatedAt": "2019-12-20T23:47:13.000Z"}}, "canReply": true, "totalReplyCount": 0, "isPublic": true}}, {"kind": "youtube#commentThread", "etag": "\"p4VTdlkQv3HQeTEaXgvLePAydmU/CuydFM3dbo1tLrprcqu11KaecKA\"", "id": "UgyE1ydObH19-8QHrnZ4AaABAg", "snippet": {"videoId": "wDTX2ntqTmo", "topLevelComment": {"kind": "youtube#comment", "etag": "\"p4VTdlkQv3HQeTEaXgvLePAydmU/JFESi27gm1SC8c4E_R30w5g62LA\"", "id": "UgyE1ydObH19-8QHrnZ4AaABAg", "snippet": {"authorDisplayName": "Shauka Hodan", "authorProfileImageUrl": "https://yt3.ggpht.com/a/AGF-l79qHUaAVK5G8WozkH5oRm2p7BcbgqrL-z9CSw=s48-c-k-c0xffffffff-no-rj-mo", "authorChannelUrl": "http://www.youtube.com/channel/UCIxcUIVjTK-IyCQEhfyI4JA", "authorChannelId": {"value": "UCIxcUIVjTK-IyCQEhfyI4JA"}, "videoId": "wDTX2ntqTmo", "textDisplay": "Vacate the wbo and give chisora a world title fight", "textOriginal": "Vacate the wbo and give chisora a world title fight", "canRate": true, "viewerRating": "none", "likeCount": 0, "publishedAt": "2019-12-20T23:37:56.000Z", "updatedAt": "2019-12-20T23:37:56.000Z"}}, "canReply": true, "totalReplyCount": 1, "isPublic": true}}, {"kind": "youtube#commentThread", "etag": "\"p4VTdlkQv3HQeTEaXgvLePAydmU/R_LYOm9YirOYkfKhGF9pz8zfNRA\"", "id": "UgyghUi5Ej1N5mYbbe94AaABAg", "snippet": {"videoId": "wDTX2ntqTmo", "topLevelComment": {"kind": "youtube#comment", "etag": "\"p4VTdlkQv3HQeTEaXgvLePAydmU/kvRz4HVbaqd2mG9fOSynDBzLKOI\"", "id": "UgyghUi5Ej1N5mYbbe94AaABAg", "snippet": {"authorDisplayName": "Chris Ward", "authorProfileImageUrl": "https://yt3.ggpht.com/a/AGF-l79L4vKNXPsY50gycrTSurJXnnKJKhiQEc-Xzw=s48-c-k-c0xffffffff-no-rj-mo", "authorChannelUrl": "http://www.youtube.com/channel/UCJt3O3hXUDbj3xPZFxeER7g", "authorChannelId": {"value": "UCJt3O3hXUDbj3xPZFxeER7g"}, "videoId": "wDTX2ntqTmo", "textDisplay": "Listen to Hearn more than the Mrs\ud83e\udd23", "textOriginal": "Listen to Hearn more than the Mrs\ud83e\udd23", "canRate": true, "viewerRating": "none", "likeCount": 0, "publishedAt": "2019-12-20T21:53:34.000Z", "updatedAt": "2019-12-20T21:53:34.000Z"}}, "canReply": true, "totalReplyCount": 1, "isPublic": true}}, {"kind": "youtube#commentThread", "etag": "\"p4VTdlkQv3HQeTEaXgvLePAydmU/QZl6z6W1bPt3TZgwodEOnoB-uU8\"", "id": "Ugz7HxPrP6ojqvOb8l94AaABAg", "snippet": {"videoId": "wDTX2ntqTmo", "topLevelComment": {"kind": "youtube#comment", "etag": "\"p4VTdlkQv3HQeTEaXgvLePAydmU/qmYR1XVGJH-Pa4k3ri-bkhdx10s\"", "id": "Ugz7HxPrP6ojqvOb8l94AaABAg", "snippet": {"authorDisplayName": "steven scouse", "authorProfileImageUrl": "https://yt3.ggpht.com/a/AGF-l78y_wXMkjf-hTZVmrTrtGKRD1jXScaP94ec=s48-c-k-c0xffffffff-no-rj-mo", "authorChannelUrl": "http://www.youtube.com/channel/UCdBodkJMEkg5hxcCK8vzb9A", "authorChannelId": {"value": "UCdBodkJMEkg5hxcCK8vzb9A"}, "videoId": "wDTX2ntqTmo", "textDisplay": "look like aj is gonna have boaring fights now then eddiehas been trying to get pulev for over a year now i dobt know why and aj wont fight wilder or fury fact", "textOriginal": "look like aj is gonna have boaring fights now then eddiehas been trying to get pulev for over a year now i dobt know why and aj wont fight wilder or fury fact", "canRate": true, "viewerRating": "none", "likeCount": 0, "publishedAt": "2019-12-20T18:29:18.000Z", "updatedAt": "2019-12-20T18:29:18.000Z"}}, "canReply": true, "totalReplyCount": 0, "isPublic": true}}, {"kind": "youtube#commentThread", "etag": "\"p4VTdlkQv3HQeTEaXgvLePAydmU/4_d8DYKiY4G07HKKjahZRv1NzxA\"", "id": "UgwnzNY8CrcHjLb16Nx4AaABAg", "snippet": {"videoId": "wDTX2ntqTmo", "topLevelComment": {"kind": "youtube#comment", "etag": "\"p4VTdlkQv3HQeTEaXgvLePAydmU/zzGkN-Oib7TZADB8NHLtK_pVxv8\"", "id": "UgwnzNY8CrcHjLb16Nx4AaABAg", "snippet": {"authorDisplayName": "mixio hili", "authorProfileImageUrl": "https://yt3.ggpht.com/a/AGF-l7_Yzuy0F0aMd4JcEXtWjwLEZ5QONd0Eu0fgtQ=s48-c-k-c0xffffffff-no-rj-mo", "authorChannelUrl": "http://www.youtube.com/channel/UCPAvlLFtnJFQGwZb2wkMO5Q", "authorChannelId": {"value": "UCPAvlLFtnJFQGwZb2wkMO5Q"}, "videoId": "wDTX2ntqTmo", "textDisplay": "Doesn\u2019t seem like Wilder vs AJ will ever happen. Real boxing fans lose again", "textOriginal": "Doesn\u2019t seem like Wilder vs AJ will ever happen. Real boxing fans lose again", "canRate": true, "viewerRating": "none", "likeCount": 0, "publishedAt": "2019-12-20T18:07:27.000Z", "updatedAt": "2019-12-20T18:07:27.000Z"}}, "canReply": true, "totalReplyCount": 1, "isPublic": true}}, {"kind": "youtube#commentThread", "etag": "\"p4VTdlkQv3HQeTEaXgvLePAydmU/ntxyiV8mRPKSHB-l8YKYpyPB4N4\"", "id": "UgysL5j3ys01qivZEZx4AaABAg", "snippet": {"videoId": "wDTX2ntqTmo", "topLevelComment": {"kind": "youtube#comment", "etag": "\"p4VTdlkQv3HQeTEaXgvLePAydmU/m5bqvQJfxrpkgpeYRtWfEGOPRMI\"", "id": "UgysL5j3ys01qivZEZx4AaABAg", "snippet": {"authorDisplayName": "Aaron Lomax", "authorProfileImageUrl": "https://yt3.ggpht.com/a/AGF-l78Cw2FlV_V4uSJ7v1DCLe6GP0inMp-6YpU21w=s48-c-k-c0xffffffff-no-rj-mo", "authorChannelUrl": "http://www.youtube.com/channel/UCESV8sc8tZccaBQjc_mGQvw", "authorChannelId": {"value": "UCESV8sc8tZccaBQjc_mGQvw"}, "videoId": "wDTX2ntqTmo", "textDisplay": "<a href=\"https://www.youtube.com/watch?v=wDTX2ntqTmo&amp;t=4m12s\">4:12</a> good save Eddie don\u2019t mention al Haymon\ud83d\ude02", "textOriginal": "4:12 good save Eddie don\u2019t mention al Haymon\ud83d\ude02", "canRate": true, "viewerRating": "none", "likeCount": 0, "publishedAt": "2019-12-20T15:00:43.000Z", "updatedAt": "2019-12-20T15:00:43.000Z"}}, "canReply": true, "totalReplyCount": 0, "isPublic": true}}, {"kind": "youtube#commentThread", "etag": "\"p4VTdlkQv3HQeTEaXgvLePAydmU/YvVnJMQ84ACtC6miC5FekV-Gg4k\"", "id": "Ugx2QPcuZ8YX8PNJ5bZ4AaABAg", "snippet": {"videoId": "wDTX2ntqTmo", "topLevelComment": {"kind": "youtube#comment", "etag": "\"p4VTdlkQv3HQeTEaXgvLePAydmU/eV6o9GeqEN51POo0-zT3ibp2tsQ\"", "id": "Ugx2QPcuZ8YX8PNJ5bZ4AaABAg", "snippet": {"authorDisplayName": "bilias hour", "authorProfileImageUrl": "https://yt3.ggpht.com/a/AGF-l79V2g_Va6-2BK_NgEmmh5KQoB_UZ3lIzj2Hdw=s48-c-k-c0xffffffff-no-rj-mo", "authorChannelUrl": "http://www.youtube.com/channel/UCrmmyj-hs1Q0DpWjQMO3mVA", "authorChannelId": {"value": "UCrmmyj-hs1Q0DpWjQMO3mVA"}, "videoId": "wDTX2ntqTmo", "textDisplay": "Anyone want dubois fight to be over so the ad goes.", "textOriginal": "Anyone want dubois fight to be over so the ad goes.", "canRate": true, "viewerRating": "none", "likeCount": 0, "publishedAt": "2019-12-20T12:40:43.000Z", "updatedAt": "2019-12-20T12:40:43.000Z"}}, "canReply": true, "totalReplyCount": 0, "isPublic": true}}, {"kind": "youtube#commentThread", "etag": "\"p4VTdlkQv3HQeTEaXgvLePAydmU/cww9EgnF9uYb42AEFygW0_VPcsY\"", "id": "UgzMzaB5WdA-i1Bs1H54AaABAg", "snippet": {"videoId": "wDTX2ntqTmo", "topLevelComment": {"kind": "youtube#comment", "etag": "\"p4VTdlkQv3HQeTEaXgvLePAydmU/kK71oh3k385k31GXeCoOpIW2IEc\"", "id": "UgzMzaB5WdA-i1Bs1H54AaABAg", "snippet": {"authorDisplayName": "leston barzey", "authorProfileImageUrl": "https://yt3.ggpht.com/a/AGF-l78L75W5-HGXv5iBpJo-KndlARovG0_xOCvKgw=s48-c-k-c0xffffffff-no-rj-mo", "authorChannelUrl": "http://www.youtube.com/channel/UC5UnaYrmSTfgKRdbxIjKtvQ", "authorChannelId": {"value": "UC5UnaYrmSTfgKRdbxIjKtvQ"}, "videoId": "wDTX2ntqTmo", "textDisplay": "dont unification override every thing these  are eddie words this guy is taking all of u lot that believes her shit for a ride  i pity u lot honestly", "textOriginal": "dont unification override every thing these  are eddie words this guy is taking all of u lot that believes her shit for a ride  i pity u lot honestly", "canRate": true, "viewerRating": "none", "likeCount": 0, "publishedAt": "2019-12-20T06:29:07.000Z", "updatedAt": "2019-12-20T06:29:07.000Z"}}, "canReply": true, "totalReplyCount": 0, "isPublic": true}}, {"kind": "youtube#commentThread", "etag": "\"p4VTdlkQv3HQeTEaXgvLePAydmU/VKGV70UZPdSdIjWHouPQhfs7jH4\"", "id": "UgzU7fVFwiV8Y_uJYs14AaABAg", "snippet": {"videoId": "wDTX2ntqTmo", "topLevelComment": {"kind": "youtube#comment", "etag": "\"p4VTdlkQv3HQeTEaXgvLePAydmU/ddEMG_T63YRZr6ndE6ivBspU0jc\"", "id": "UgzU7fVFwiV8Y_uJYs14AaABAg", "snippet": {"authorDisplayName": "Jason Elliott", "authorProfileImageUrl": "https://yt3.ggpht.com/a/AGF-l780UwzsQoabDM0eDbGqSQhm29NkULeWP_2xbw=s48-c-k-c0xffffffff-no-rj-mo", "authorChannelUrl": "http://www.youtube.com/channel/UC8iYMq-lAbcdQGCqkKEpr5Q", "authorChannelId": {"value": "UC8iYMq-lAbcdQGCqkKEpr5Q"}, "videoId": "wDTX2ntqTmo", "textDisplay": "We know exactly who you&#39;re talking about Eddie...", "textOriginal": "We know exactly who you're talking about Eddie...", "canRate": true, "viewerRating": "none", "likeCount": 0, "publishedAt": "2019-12-20T04:44:21.000Z", "updatedAt": "2019-12-20T04:44:39.000Z"}}, "canReply": true, "totalReplyCount": 1, "isPublic": true}}]